flippydot/__init__.py
flippydot/flippydot.py
flippydot/flippymodule.py
flippydot-0.1.1.dist-info/LICENSE
flippydot-0.1.1.dist-info/METADATA
flippydot-0.1.1.dist-info/WHEEL
flippydot-0.1.1.dist-info/top_level.txt
flippydot-0.1.1.dist-info/RECORD
