Metadata-Version: 2.1
Name: flippydot
Version: 0.1.1
Summary: A package that can be used to control AlfaZeta FlipDots
Home-page: https://github.com/chrishemmings/flipPyDot
Author: Chris Hemmings
Classifier: Programming Language :: Python :: 3
Classifier: License :: OSI Approved :: MIT License
Classifier: Operating System :: OS Independent
Requires-Python: >=3.6
License-File: LICENSE
Requires-Dist: numpy >=1.18
Requires-Dist: pyserial >=3.4
